examples/__init__.py
examples/checkbox.py
examples/confirm.py
examples/editor.py
examples/expand.py
examples/hierarchical.py
examples/input.py
examples/list.py
examples/password.py
examples/pizza.py
examples/rawlist.py
examples/when.py
python_inquirer/__init__.py
python_inquirer/color_print.py
python_inquirer/prompt.py
python_inquirer/separator.py
python_inquirer/utils.py
python_inquirer/prompts/__init__.py
python_inquirer/prompts/checkbox.py
python_inquirer/prompts/common.py
python_inquirer/prompts/confirm.py
python_inquirer/prompts/editor.py
python_inquirer/prompts/expand.py
python_inquirer/prompts/input.py
python_inquirer/prompts/list.py
python_inquirer/prompts/password.py
python_inquirer/prompts/rawlist.py
python_inquirer-1.0.3.dist-info/DESCRIPTION.rst
python_inquirer-1.0.3.dist-info/METADATA
python_inquirer-1.0.3.dist-info/RECORD
python_inquirer-1.0.3.dist-info/WHEEL
python_inquirer-1.0.3.dist-info/dependency_links.txt
python_inquirer-1.0.3.dist-info/metadata.json
python_inquirer-1.0.3.dist-info/top_level.txt
